versecbot/__init__.py
versecbot/__main__.py
versecbot/client.py
versecbot/settings.py
versecbot/util.py
versecbot-0.4.1.dist-info/METADATA
versecbot-0.4.1.dist-info/WHEEL
versecbot-0.4.1.dist-info/licenses/LICENSE.md
versecbot-0.4.1.dist-info/RECORD
