Metadata-Version: 2.4
Name: versecbot
Version: 0.4.1
Summary: Extendable Discord Bot to manage common moderation tasks
Project-URL: Homepage, https://github.com/Museus/VerSecBot
Project-URL: Issues, https://github.com/Museus/VerSecBot/issues
Author-email: Museus <versecbot@museus.dev>
License-Expression: MIT
License-File: LICENSE.md
Classifier: Operating System :: OS Independent
Classifier: Programming Language :: Python :: 3
Requires-Python: >=3.8
Requires-Dist: discord-py<3,>=2
Requires-Dist: pydantic-settings<3,>=2
Requires-Dist: versecbot-interface>=0.4.0
